decorator_parser/__init__.py
decorator_parser/errors.py
decorator_parser/parse.py
decorator_parser/utils.py
decorator_parser-1.2.0.dist-info/LICENSE
decorator_parser-1.2.0.dist-info/METADATA
decorator_parser-1.2.0.dist-info/WHEEL
decorator_parser-1.2.0.dist-info/top_level.txt
decorator_parser-1.2.0.dist-info/RECORD
