Metadata-Version: 2.1
Name: decorator_parser
Version: 1.2.0
Summary: Parser for text files with decorators into Python dictionaries
Author-email: Michal Kostyk <m.kostyk22@gmail.com>
Project-URL: Homepage, https://github.com/mkostyk/decorators-parser
Project-URL: Bug Tracker, https://github.com/mkostyk/decorators-parser/issues
Classifier: Programming Language :: Python :: 3
Classifier: Operating System :: OS Independent
Requires-Python: >=3.7
License-File: LICENSE
